odoo/addons/web_widget_remaining_days_exact_date/README.rst
odoo/addons/web_widget_remaining_days_exact_date/__init__.py
odoo/addons/web_widget_remaining_days_exact_date/__manifest__.py
odoo/addons/web_widget_remaining_days_exact_date/i18n/it.po
odoo/addons/web_widget_remaining_days_exact_date/i18n/web_widget_remaining_days_exact_date.pot
odoo/addons/web_widget_remaining_days_exact_date/readme/CONTRIBUTORS.rst
odoo/addons/web_widget_remaining_days_exact_date/readme/DESCRIPTION.rst
odoo/addons/web_widget_remaining_days_exact_date/readme/USAGE.rst
odoo/addons/web_widget_remaining_days_exact_date/static/description/icon.png
odoo/addons/web_widget_remaining_days_exact_date/static/description/index.html
odoo/addons/web_widget_remaining_days_exact_date/static/src/remaining_days/remaining_days.esm.js
odoo_addon_web_widget_remaining_days_exact_date-16.0.1.0.0.3.dist-info/METADATA
odoo_addon_web_widget_remaining_days_exact_date-16.0.1.0.0.3.dist-info/WHEEL
odoo_addon_web_widget_remaining_days_exact_date-16.0.1.0.0.3.dist-info/top_level.txt
odoo_addon_web_widget_remaining_days_exact_date-16.0.1.0.0.3.dist-info/RECORD
